openface/__init__.py
openface/feature_extraction.py
openface-0.0.0.dist-info/METADATA
openface-0.0.0.dist-info/WHEEL
openface-0.0.0.dist-info/top_level.txt
openface-0.0.0.dist-info/RECORD
